{
  "transactions": [
    {
      "id": 1,
      "description": "Salário",
      "type": "income",
      "category": "Venda",
      "price": 2450,
      "createdAt": "2022-12-11"
    },
    {
      "id": 2,
      "description": "Estudonalta",
      "type": "outcome",
      "category": "Estudo",
      "price": 29.99,
      "createdAt": "2022-12-06"
    },
    {
      "id": 3,
      "description": "Muay-Thai",
      "type": "outcome",
      "category": "Esporte",
      "price": 29.99,
      "createdAt": "2022-12-06"
    },
    {
      "id": 4,
      "description": "Faculdade",
      "type": "outcome",
      "category": "Estudo",
      "price": 220,
      "createdAt": "2022-12-06"
    },
    {
      "id": 5,
      "description": "Academia",
      "type": "outcome",
      "category": "Esporte",
      "price": 100,
      "createdAt": "2022-12-06"
    },
    {
      "id": 6,
      "description": "Gás",
      "type": "outcome",
      "category": "Básico",
      "price": 125,
      "createdAt": "2022-12-06"
    },
    {
      "id": 7,
      "description": "Aluguel",
      "type": "outcome",
      "category": "Básico",
      "price": 500,
      "createdAt": "2022-12-06"
    },
    {
      "id": 8,
      "description": "Comida",
      "type": "outcome",
      "category": "Alimentos",
      "price": 320,
      "createdAt": "2022-12-06T07:18:56"
    },
    {
      "id": 9,
      "description": "Netflix",
      "type": "outcome",
      "category": "Lazer",
      "price": 39.99,
      "createdAt": "2022-12-06T07:18:56"
    },
    {
      "description": "Imposto de Renda",
      "price": 26,
      "category": "Obrigatório",
      "type": "outcome",
      "createdAt": "2022-12-22T01:15:05.770Z",
      "id": 10
    },
    {
      "description": "INSS",
      "price": 294,
      "category": "Obrigatório",
      "type": "outcome",
      "createdAt": "2022-12-22T10:38:34.913Z",
      "id": 11
    }
  ]
}